{
  "sha": "0a1df0d6118567fa6ea255b9081b8da3c9c80554",
  "timestamp": "2026-03-29 12:41",
  "changelog": [
    "feat(wispr-addons): add menu bar icon with clickable clean repaste actions"
  ],
  "branches": [
    {
      "branch": "fix-transcription-lang-sync",
      "sha": "3a35f5c",
      "minutes": 342
    },
    {
      "branch": "session-id-in-path",
      "sha": "c665635",
      "minutes": 320
    },
    {
      "branch": "session-id-in-path-v3",
      "sha": "96b27e4",
      "minutes": 255
    },
    {
      "branch": "fix-ci-run-23695885613",
      "sha": "916b7b1",
      "minutes": 99
    },
    {
      "branch": "adjust-topic-names",
      "sha": "6d91844",
      "minutes": 94
    },
    {
      "branch": "fix-emoji-overlay-hover",
      "sha": "1fcd15e",
      "minutes": 84
    },
    {
      "branch": "demo-slide-log",
      "sha": "22f7805",
      "minutes": 61
    },
    {
      "branch": "participant-file-upload",
      "sha": "6441120",
      "minutes": 60
    },
    {
      "branch": "upload-tooltip-onboarding",
      "sha": "991ef8e",
      "minutes": 59
    },
    {
      "branch": "fix-ci-job",
      "sha": "582b580",
      "minutes": 53
    },
    {
      "branch": "host-label-always-visible",
      "sha": "0c876ee",
      "minutes": 40
    },
    {
      "branch": "emoji-overflow-dots",
      "sha": "25b9b9a",
      "minutes": 39
    },
    {
      "branch": "slides-hover-tooltips",
      "sha": "0652ac9",
      "minutes": 36
    },
    {
      "branch": "fix-ui-layout-cutoff",
      "sha": "739e719",
      "minutes": 27
    },
    {
      "branch": "ai-coding-category-line",
      "sha": "8fa3b8e",
      "minutes": 20
    },
    {
      "branch": "wispr-menu-clickable",
      "sha": "0a1df0d",
      "minutes": 19
    },
    {
      "branch": "remove-host-heart-drone",
      "sha": "9d8de3e",
      "minutes": 15
    },
    {
      "branch": "shrink-topic-height-5pct",
      "sha": "466fbe7",
      "minutes": 14
    },
    {
      "branch": "pdf-fit-width-btn",
      "sha": "60d7e4a",
      "minutes": 10
    },
    {
      "branch": "fix-slides-scroll-drift",
      "sha": "9babc87",
      "minutes": 10
    }
  ]
}